dependent_bterms/__init__.py
dependent_bterms/dependent_variable_ring.py
dependent_bterms/structures.py
dependent_bterms/utils.py
dependent_bterms-1.0.2.dist-info/METADATA
dependent_bterms-1.0.2.dist-info/WHEEL
dependent_bterms-1.0.2.dist-info/licenses/COPYING.txt
dependent_bterms-1.0.2.dist-info/RECORD
