Metadata-Version: 2.4
Name: dependent-bterms
Version: 1.0.2
Summary: An extension to SageMath's module for computations with asymptotic expansions. Provides a special AsymptoticRing that allows to specify a secondary, dependent (monomially bounded) variable.
Project-URL: Repository, https://github.com/behackl/dependent_bterms
Author-email: Benjamin Hackl <devel@benjamin-hackl.at>
License-Expression: GPL-3.0-or-later
License-File: COPYING.txt
Requires-Python: ~=3.9
Provides-Extra: passagemath
Requires-Dist: passagemath-graphs~=10.4; extra == 'passagemath'
Requires-Dist: passagemath-repl~=10.4; extra == 'passagemath'
Requires-Dist: passagemath-symbolics~=10.4; extra == 'passagemath'
